threadbare/__init__.py
threadbare/common.py
threadbare/execute.py
threadbare/operations.py
threadbare/state.py
threadbare-4.1.0.dist-info/LICENCE.txt
threadbare-4.1.0.dist-info/METADATA
threadbare-4.1.0.dist-info/WHEEL
threadbare-4.1.0.dist-info/top_level.txt
threadbare-4.1.0.dist-info/RECORD
