Metadata-Version: 2.1
Name: threadbare
Version: 4.1.0
Summary: A Fabric and Paramiko replacement library
Home-page: https://github.com/elifesciences/threadbare
Maintainer: Luke
Maintainer-email: lsh-0@users.noreply.github.com
License: AGPLv3
Classifier: Intended Audience :: System Administrators
Classifier: Programming Language :: Python :: 3
Classifier: Operating System :: POSIX
Classifier: License :: OSI Approved :: GNU Affero General Public License v3
License-File: LICENCE.txt
Requires-Dist: parallel-ssh >=2.12.0
